krypto_rates_client/__init__.py
krypto_rates_client/__version__.py
krypto_rates_client/client.py
krypto_rates_client/types.py
krypto_rates_client/utils.py
krypto_rates_client-1.1.5.dist-info/METADATA
krypto_rates_client-1.1.5.dist-info/WHEEL
krypto_rates_client-1.1.5.dist-info/top_level.txt
krypto_rates_client-1.1.5.dist-info/RECORD
