Metadata-Version: 2.1
Name: krypto-rates-client
Version: 1.1.5
Summary: Krypto Rates Python Client
Home-page: https://github.com/snake575/krypto-rates
Author: Raptor Systems SpA
Author-email: raptor@raptorsystems.cl
License: MIT
Platform: UNKNOWN
Classifier: License :: OSI Approved :: MIT License
Classifier: Programming Language :: Python
Classifier: Programming Language :: Python :: 3
Classifier: Programming Language :: Python :: 3.7
Classifier: Programming Language :: Python :: 3.8
Classifier: Programming Language :: Python :: Implementation :: CPython
Classifier: Programming Language :: Python :: Implementation :: PyPy
Requires-Python: >=3.7.0
Requires-Dist: requests
Requires-Dist: requests-toolbelt
Requires-Dist: typing-extensions
